{
  "name": "Mercadian Masques Draft Booster",
  "code": "mmq-draft",
  "set_code": "mmq",
  "set_name": "Mercadian Masques",
  "boosters": [
    {
      "sheets": {
        "rare": 1,
        "uncommon": 3,
        "common": 11
      },
      "weight": 854667,
      "sheet_order": [
        "rare",
        "uncommon",
        "common"
      ]
    },
    {
      "sheets": {
        "rare": 1,
        "uncommon": 3,
        "common": 10,
        "foil_common_or_basic": 1
      },
      "weight": 105633,
      "sheet_order": [
        "rare",
        "uncommon",
        "common",
        "foil_common_or_basic"
      ]
    },
    {
      "sheets": {
        "rare": 1,
        "uncommon": 2,
        "foil_uncommon": 1,
        "common": 11
      },
      "weight": 26433,
      "sheet_order": [
        "rare",
        "uncommon",
        "foil_uncommon",
        "common"
      ]
    },
    {
      "sheets": {
        "rare": 1,
        "uncommon": 2,
        "foil_uncommon": 1,
        "common": 10,
        "foil_common_or_basic": 1
      },
      "weight": 3267,
      "sheet_order": [
        "rare",
        "uncommon",
        "foil_uncommon",
        "common",
        "foil_common_or_basic"
      ]
    },
    {
      "sheets": {
        "foil_rare": 1,
        "uncommon": 3,
        "common": 11
      },
      "weight": 8633,
      "sheet_order": [
        "foil_rare",
        "uncommon",
        "common"
      ]
    },
    {
      "sheets": {
        "foil_rare": 1,
        "uncommon": 3,
        "common": 10,
        "foil_common_or_basic": 1
      },
      "weight": 1067,
      "sheet_order": [
        "foil_rare",
        "uncommon",
        "common",
        "foil_common_or_basic"
      ]
    },
    {
      "sheets": {
        "foil_rare": 1,
        "uncommon": 2,
        "foil_uncommon": 1,
        "common": 11
      },
      "weight": 267,
      "sheet_order": [
        "foil_rare",
        "uncommon",
        "foil_uncommon",
        "common"
      ]
    },
    {
      "sheets": {
        "foil_rare": 1,
        "uncommon": 2,
        "foil_uncommon": 1,
        "common": 10,
        "foil_common_or_basic": 1
      },
      "weight": 33,
      "sheet_order": [
        "foil_rare",
        "uncommon",
        "foil_uncommon",
        "common",
        "foil_common_or_basic"
      ]
    }
  ],
  "sheets": {
    "rare": {
      "total_weight": 110,
      "cards": {
        "mmq:105": 1,
        "mmq:106": 1,
        "mmq:11": 1,
        "mmq:110": 1,
        "mmq:112": 1,
        "mmq:116": 1,
        "mmq:123": 1,
        "mmq:125": 1,
        "mmq:127": 1,
        "mmq:128": 1,
        "mmq:13": 1,
        "mmq:133": 1,
        "mmq:135": 1,
        "mmq:136": 1,
        "mmq:14": 1,
        "mmq:140": 1,
        "mmq:144": 1,
        "mmq:146": 1,
        "mmq:149": 1,
        "mmq:15": 1,
        "mmq:150": 1,
        "mmq:160": 1,
        "mmq:166": 1,
        "mmq:168": 1,
        "mmq:169": 1,
        "mmq:174": 1,
        "mmq:176": 1,
        "mmq:177": 1,
        "mmq:178": 1,
        "mmq:180": 1,
        "mmq:185": 1,
        "mmq:187": 1,
        "mmq:19": 1,
        "mmq:200": 1,
        "mmq:202": 1,
        "mmq:207": 1,
        "mmq:208": 1,
        "mmq:21": 1,
        "mmq:211": 1,
        "mmq:214": 1,
        "mmq:216": 1,
        "mmq:217": 1,
        "mmq:218": 1,
        "mmq:221": 1,
        "mmq:230": 1,
        "mmq:233": 1,
        "mmq:235": 1,
        "mmq:236": 1,
        "mmq:237": 1,
        "mmq:24": 1,
        "mmq:240": 1,
        "mmq:244": 1,
        "mmq:246": 1,
        "mmq:247": 1,
        "mmq:248": 1,
        "mmq:25": 1,
        "mmq:259": 1,
        "mmq:260": 1,
        "mmq:261": 1,
        "mmq:264": 1,
        "mmq:274": 1,
        "mmq:283": 1,
        "mmq:284": 1,
        "mmq:286": 1,
        "mmq:288": 1,
        "mmq:291": 1,
        "mmq:292": 1,
        "mmq:293": 1,
        "mmq:294": 1,
        "mmq:295": 1,
        "mmq:296": 1,
        "mmq:298": 1,
        "mmq:299": 1,
        "mmq:3": 1,
        "mmq:302": 1,
        "mmq:303": 1,
        "mmq:304": 1,
        "mmq:305": 1,
        "mmq:306": 1,
        "mmq:307": 1,
        "mmq:309": 1,
        "mmq:311": 1,
        "mmq:312": 1,
        "mmq:313": 1,
        "mmq:315": 1,
        "mmq:316": 1,
        "mmq:320": 1,
        "mmq:324": 1,
        "mmq:330": 1,
        "mmq:40": 1,
        "mmq:41": 1,
        "mmq:44": 1,
        "mmq:47": 1,
        "mmq:49": 1,
        "mmq:56": 1,
        "mmq:58": 1,
        "mmq:62": 1,
        "mmq:66": 1,
        "mmq:70": 1,
        "mmq:77": 1,
        "mmq:79": 1,
        "mmq:8": 1,
        "mmq:86": 1,
        "mmq:87": 1,
        "mmq:89": 1,
        "mmq:9": 1,
        "mmq:92": 1,
        "mmq:96": 1,
        "mmq:97": 1,
        "mmq:99": 1
      }
    },
    "uncommon": {
      "total_weight": 110,
      "cards": {
        "mmq:1": 1,
        "mmq:10": 1,
        "mmq:100": 1,
        "mmq:103": 1,
        "mmq:104": 1,
        "mmq:108": 1,
        "mmq:111": 1,
        "mmq:113": 1,
        "mmq:119": 1,
        "mmq:121": 1,
        "mmq:122": 1,
        "mmq:126": 1,
        "mmq:130": 1,
        "mmq:132": 1,
        "mmq:134": 1,
        "mmq:137": 1,
        "mmq:138": 1,
        "mmq:142": 1,
        "mmq:143": 1,
        "mmq:148": 1,
        "mmq:151": 1,
        "mmq:152": 1,
        "mmq:153": 1,
        "mmq:154": 1,
        "mmq:155": 1,
        "mmq:158": 1,
        "mmq:165": 1,
        "mmq:172": 1,
        "mmq:183": 1,
        "mmq:184": 1,
        "mmq:188": 1,
        "mmq:193": 1,
        "mmq:194": 1,
        "mmq:197": 1,
        "mmq:198": 1,
        "mmq:204": 1,
        "mmq:205": 1,
        "mmq:206": 1,
        "mmq:209": 1,
        "mmq:210": 1,
        "mmq:22": 1,
        "mmq:222": 1,
        "mmq:223": 1,
        "mmq:224": 1,
        "mmq:225": 1,
        "mmq:226": 1,
        "mmq:228": 1,
        "mmq:231": 1,
        "mmq:232": 1,
        "mmq:234": 1,
        "mmq:241": 1,
        "mmq:243": 1,
        "mmq:250": 1,
        "mmq:253": 1,
        "mmq:256": 1,
        "mmq:257": 1,
        "mmq:258": 1,
        "mmq:26": 1,
        "mmq:262": 1,
        "mmq:266": 1,
        "mmq:267": 1,
        "mmq:27": 1,
        "mmq:270": 1,
        "mmq:271": 1,
        "mmq:276": 1,
        "mmq:277": 1,
        "mmq:278": 1,
        "mmq:281": 1,
        "mmq:287": 1,
        "mmq:289": 1,
        "mmq:29": 1,
        "mmq:290": 1,
        "mmq:297": 1,
        "mmq:300": 1,
        "mmq:301": 1,
        "mmq:308": 1,
        "mmq:310": 1,
        "mmq:314": 1,
        "mmq:317": 1,
        "mmq:318": 1,
        "mmq:32": 1,
        "mmq:321": 1,
        "mmq:325": 1,
        "mmq:327": 1,
        "mmq:329": 1,
        "mmq:35": 1,
        "mmq:36": 1,
        "mmq:4": 1,
        "mmq:42": 1,
        "mmq:45": 1,
        "mmq:46": 1,
        "mmq:5": 1,
        "mmq:51": 1,
        "mmq:54": 1,
        "mmq:55": 1,
        "mmq:57": 1,
        "mmq:64": 1,
        "mmq:65": 1,
        "mmq:68": 1,
        "mmq:7": 1,
        "mmq:71": 1,
        "mmq:74": 1,
        "mmq:78": 1,
        "mmq:80": 1,
        "mmq:81": 1,
        "mmq:83": 1,
        "mmq:85": 1,
        "mmq:94": 1,
        "mmq:95": 1,
        "mmq:98": 1
      }
    },
    "common": {
      "balance_colors": true,
      "total_weight": 110,
      "cards": {
        "mmq:101": 1,
        "mmq:102": 1,
        "mmq:107": 1,
        "mmq:109": 1,
        "mmq:114": 1,
        "mmq:115": 1,
        "mmq:117": 1,
        "mmq:118": 1,
        "mmq:12": 1,
        "mmq:120": 1,
        "mmq:124": 1,
        "mmq:129": 1,
        "mmq:131": 1,
        "mmq:139": 1,
        "mmq:141": 1,
        "mmq:145": 1,
        "mmq:147": 1,
        "mmq:156": 1,
        "mmq:157": 1,
        "mmq:159": 1,
        "mmq:16": 1,
        "mmq:161": 1,
        "mmq:162": 1,
        "mmq:163": 1,
        "mmq:164": 1,
        "mmq:167": 1,
        "mmq:17": 1,
        "mmq:170": 1,
        "mmq:171": 1,
        "mmq:173": 1,
        "mmq:175": 1,
        "mmq:179": 1,
        "mmq:18": 1,
        "mmq:181": 1,
        "mmq:182": 1,
        "mmq:186": 1,
        "mmq:189": 1,
        "mmq:190": 1,
        "mmq:191": 1,
        "mmq:192": 1,
        "mmq:195": 1,
        "mmq:196": 1,
        "mmq:199": 1,
        "mmq:2": 1,
        "mmq:20": 1,
        "mmq:201": 1,
        "mmq:203": 1,
        "mmq:212": 1,
        "mmq:213": 1,
        "mmq:215": 1,
        "mmq:219": 1,
        "mmq:220": 1,
        "mmq:227": 1,
        "mmq:229": 1,
        "mmq:23": 1,
        "mmq:238": 1,
        "mmq:239": 1,
        "mmq:242": 1,
        "mmq:245": 1,
        "mmq:249": 1,
        "mmq:251": 1,
        "mmq:252": 1,
        "mmq:254": 1,
        "mmq:255": 1,
        "mmq:263": 1,
        "mmq:265": 1,
        "mmq:268": 1,
        "mmq:269": 1,
        "mmq:272": 1,
        "mmq:273": 1,
        "mmq:275": 1,
        "mmq:279": 1,
        "mmq:28": 1,
        "mmq:280": 1,
        "mmq:282": 1,
        "mmq:285": 1,
        "mmq:30": 1,
        "mmq:31": 1,
        "mmq:319": 1,
        "mmq:322": 1,
        "mmq:323": 1,
        "mmq:326": 1,
        "mmq:328": 1,
        "mmq:33": 1,
        "mmq:34": 1,
        "mmq:37": 1,
        "mmq:38": 1,
        "mmq:39": 1,
        "mmq:43": 1,
        "mmq:48": 1,
        "mmq:50": 1,
        "mmq:52": 1,
        "mmq:53": 1,
        "mmq:59": 1,
        "mmq:6": 1,
        "mmq:60": 1,
        "mmq:61": 1,
        "mmq:63": 1,
        "mmq:67": 1,
        "mmq:69": 1,
        "mmq:72": 1,
        "mmq:73": 1,
        "mmq:75": 1,
        "mmq:76": 1,
        "mmq:82": 1,
        "mmq:84": 1,
        "mmq:88": 1,
        "mmq:90": 1,
        "mmq:91": 1,
        "mmq:93": 1
      }
    },
    "foil_common_or_basic": {
      "total_weight": 130,
      "cards": {
        "mmq:101:foil": 1,
        "mmq:102:foil": 1,
        "mmq:107:foil": 1,
        "mmq:109:foil": 1,
        "mmq:114:foil": 1,
        "mmq:115:foil": 1,
        "mmq:117:foil": 1,
        "mmq:118:foil": 1,
        "mmq:120:foil": 1,
        "mmq:124:foil": 1,
        "mmq:129:foil": 1,
        "mmq:12:foil": 1,
        "mmq:131:foil": 1,
        "mmq:139:foil": 1,
        "mmq:141:foil": 1,
        "mmq:145:foil": 1,
        "mmq:147:foil": 1,
        "mmq:156:foil": 1,
        "mmq:157:foil": 1,
        "mmq:159:foil": 1,
        "mmq:161:foil": 1,
        "mmq:162:foil": 1,
        "mmq:163:foil": 1,
        "mmq:164:foil": 1,
        "mmq:167:foil": 1,
        "mmq:16:foil": 1,
        "mmq:170:foil": 1,
        "mmq:171:foil": 1,
        "mmq:173:foil": 1,
        "mmq:175:foil": 1,
        "mmq:179:foil": 1,
        "mmq:17:foil": 1,
        "mmq:181:foil": 1,
        "mmq:182:foil": 1,
        "mmq:186:foil": 1,
        "mmq:189:foil": 1,
        "mmq:18:foil": 1,
        "mmq:190:foil": 1,
        "mmq:191:foil": 1,
        "mmq:192:foil": 1,
        "mmq:195:foil": 1,
        "mmq:196:foil": 1,
        "mmq:199:foil": 1,
        "mmq:201:foil": 1,
        "mmq:203:foil": 1,
        "mmq:20:foil": 1,
        "mmq:212:foil": 1,
        "mmq:213:foil": 1,
        "mmq:215:foil": 1,
        "mmq:219:foil": 1,
        "mmq:220:foil": 1,
        "mmq:227:foil": 1,
        "mmq:229:foil": 1,
        "mmq:238:foil": 1,
        "mmq:239:foil": 1,
        "mmq:23:foil": 1,
        "mmq:242:foil": 1,
        "mmq:245:foil": 1,
        "mmq:249:foil": 1,
        "mmq:251:foil": 1,
        "mmq:252:foil": 1,
        "mmq:254:foil": 1,
        "mmq:255:foil": 1,
        "mmq:263:foil": 1,
        "mmq:265:foil": 1,
        "mmq:268:foil": 1,
        "mmq:269:foil": 1,
        "mmq:272:foil": 1,
        "mmq:273:foil": 1,
        "mmq:275:foil": 1,
        "mmq:279:foil": 1,
        "mmq:280:foil": 1,
        "mmq:282:foil": 1,
        "mmq:285:foil": 1,
        "mmq:28:foil": 1,
        "mmq:2:foil": 1,
        "mmq:30:foil": 1,
        "mmq:319:foil": 1,
        "mmq:31:foil": 1,
        "mmq:322:foil": 1,
        "mmq:323:foil": 1,
        "mmq:326:foil": 1,
        "mmq:328:foil": 1,
        "mmq:331:foil": 1,
        "mmq:332:foil": 1,
        "mmq:333:foil": 1,
        "mmq:334:foil": 1,
        "mmq:335:foil": 1,
        "mmq:336:foil": 1,
        "mmq:337:foil": 1,
        "mmq:338:foil": 1,
        "mmq:339:foil": 1,
        "mmq:33:foil": 1,
        "mmq:340:foil": 1,
        "mmq:341:foil": 1,
        "mmq:342:foil": 1,
        "mmq:343:foil": 1,
        "mmq:344:foil": 1,
        "mmq:345:foil": 1,
        "mmq:346:foil": 1,
        "mmq:347:foil": 1,
        "mmq:348:foil": 1,
        "mmq:349:foil": 1,
        "mmq:34:foil": 1,
        "mmq:350:foil": 1,
        "mmq:37:foil": 1,
        "mmq:38:foil": 1,
        "mmq:39:foil": 1,
        "mmq:43:foil": 1,
        "mmq:48:foil": 1,
        "mmq:50:foil": 1,
        "mmq:52:foil": 1,
        "mmq:53:foil": 1,
        "mmq:59:foil": 1,
        "mmq:60:foil": 1,
        "mmq:61:foil": 1,
        "mmq:63:foil": 1,
        "mmq:67:foil": 1,
        "mmq:69:foil": 1,
        "mmq:6:foil": 1,
        "mmq:72:foil": 1,
        "mmq:73:foil": 1,
        "mmq:75:foil": 1,
        "mmq:76:foil": 1,
        "mmq:82:foil": 1,
        "mmq:84:foil": 1,
        "mmq:88:foil": 1,
        "mmq:90:foil": 1,
        "mmq:91:foil": 1,
        "mmq:93:foil": 1
      }
    },
    "foil_uncommon": {
      "total_weight": 110,
      "cards": {
        "mmq:100:foil": 1,
        "mmq:103:foil": 1,
        "mmq:104:foil": 1,
        "mmq:108:foil": 1,
        "mmq:10:foil": 1,
        "mmq:111:foil": 1,
        "mmq:113:foil": 1,
        "mmq:119:foil": 1,
        "mmq:121:foil": 1,
        "mmq:122:foil": 1,
        "mmq:126:foil": 1,
        "mmq:130:foil": 1,
        "mmq:132:foil": 1,
        "mmq:134:foil": 1,
        "mmq:137:foil": 1,
        "mmq:138:foil": 1,
        "mmq:142:foil": 1,
        "mmq:143:foil": 1,
        "mmq:148:foil": 1,
        "mmq:151:foil": 1,
        "mmq:152:foil": 1,
        "mmq:153:foil": 1,
        "mmq:154:foil": 1,
        "mmq:155:foil": 1,
        "mmq:158:foil": 1,
        "mmq:165:foil": 1,
        "mmq:172:foil": 1,
        "mmq:183:foil": 1,
        "mmq:184:foil": 1,
        "mmq:188:foil": 1,
        "mmq:193:foil": 1,
        "mmq:194:foil": 1,
        "mmq:197:foil": 1,
        "mmq:198:foil": 1,
        "mmq:1:foil": 1,
        "mmq:204:foil": 1,
        "mmq:205:foil": 1,
        "mmq:206:foil": 1,
        "mmq:209:foil": 1,
        "mmq:210:foil": 1,
        "mmq:222:foil": 1,
        "mmq:223:foil": 1,
        "mmq:224:foil": 1,
        "mmq:225:foil": 1,
        "mmq:226:foil": 1,
        "mmq:228:foil": 1,
        "mmq:22:foil": 1,
        "mmq:231:foil": 1,
        "mmq:232:foil": 1,
        "mmq:234:foil": 1,
        "mmq:241:foil": 1,
        "mmq:243:foil": 1,
        "mmq:250:foil": 1,
        "mmq:253:foil": 1,
        "mmq:256:foil": 1,
        "mmq:257:foil": 1,
        "mmq:258:foil": 1,
        "mmq:262:foil": 1,
        "mmq:266:foil": 1,
        "mmq:267:foil": 1,
        "mmq:26:foil": 1,
        "mmq:270:foil": 1,
        "mmq:271:foil": 1,
        "mmq:276:foil": 1,
        "mmq:277:foil": 1,
        "mmq:278:foil": 1,
        "mmq:27:foil": 1,
        "mmq:281:foil": 1,
        "mmq:287:foil": 1,
        "mmq:289:foil": 1,
        "mmq:290:foil": 1,
        "mmq:297:foil": 1,
        "mmq:29:foil": 1,
        "mmq:300:foil": 1,
        "mmq:301:foil": 1,
        "mmq:308:foil": 1,
        "mmq:310:foil": 1,
        "mmq:314:foil": 1,
        "mmq:317:foil": 1,
        "mmq:318:foil": 1,
        "mmq:321:foil": 1,
        "mmq:325:foil": 1,
        "mmq:327:foil": 1,
        "mmq:329:foil": 1,
        "mmq:32:foil": 1,
        "mmq:35:foil": 1,
        "mmq:36:foil": 1,
        "mmq:42:foil": 1,
        "mmq:45:foil": 1,
        "mmq:46:foil": 1,
        "mmq:4:foil": 1,
        "mmq:51:foil": 1,
        "mmq:54:foil": 1,
        "mmq:55:foil": 1,
        "mmq:57:foil": 1,
        "mmq:5:foil": 1,
        "mmq:64:foil": 1,
        "mmq:65:foil": 1,
        "mmq:68:foil": 1,
        "mmq:71:foil": 1,
        "mmq:74:foil": 1,
        "mmq:78:foil": 1,
        "mmq:7:foil": 1,
        "mmq:80:foil": 1,
        "mmq:81:foil": 1,
        "mmq:83:foil": 1,
        "mmq:85:foil": 1,
        "mmq:94:foil": 1,
        "mmq:95:foil": 1,
        "mmq:98:foil": 1
      }
    },
    "foil_rare": {
      "total_weight": 110,
      "cards": {
        "mmq:105:foil": 1,
        "mmq:106:foil": 1,
        "mmq:110:foil": 1,
        "mmq:112:foil": 1,
        "mmq:116:foil": 1,
        "mmq:11:foil": 1,
        "mmq:123:foil": 1,
        "mmq:125:foil": 1,
        "mmq:127:foil": 1,
        "mmq:128:foil": 1,
        "mmq:133:foil": 1,
        "mmq:135:foil": 1,
        "mmq:136:foil": 1,
        "mmq:13:foil": 1,
        "mmq:140:foil": 1,
        "mmq:144:foil": 1,
        "mmq:146:foil": 1,
        "mmq:149:foil": 1,
        "mmq:14:foil": 1,
        "mmq:150:foil": 1,
        "mmq:15:foil": 1,
        "mmq:160:foil": 1,
        "mmq:166:foil": 1,
        "mmq:168:foil": 1,
        "mmq:169:foil": 1,
        "mmq:174:foil": 1,
        "mmq:176:foil": 1,
        "mmq:177:foil": 1,
        "mmq:178:foil": 1,
        "mmq:180:foil": 1,
        "mmq:185:foil": 1,
        "mmq:187:foil": 1,
        "mmq:19:foil": 1,
        "mmq:200:foil": 1,
        "mmq:202:foil": 1,
        "mmq:207:foil": 1,
        "mmq:208:foil": 1,
        "mmq:211:foil": 1,
        "mmq:214:foil": 1,
        "mmq:216:foil": 1,
        "mmq:217:foil": 1,
        "mmq:218:foil": 1,
        "mmq:21:foil": 1,
        "mmq:221:foil": 1,
        "mmq:230:foil": 1,
        "mmq:233:foil": 1,
        "mmq:235:foil": 1,
        "mmq:236:foil": 1,
        "mmq:237:foil": 1,
        "mmq:240:foil": 1,
        "mmq:244:foil": 1,
        "mmq:246:foil": 1,
        "mmq:247:foil": 1,
        "mmq:248:foil": 1,
        "mmq:24:foil": 1,
        "mmq:259:foil": 1,
        "mmq:25:foil": 1,
        "mmq:260:foil": 1,
        "mmq:261:foil": 1,
        "mmq:264:foil": 1,
        "mmq:274:foil": 1,
        "mmq:283:foil": 1,
        "mmq:284:foil": 1,
        "mmq:286:foil": 1,
        "mmq:288:foil": 1,
        "mmq:291:foil": 1,
        "mmq:292:foil": 1,
        "mmq:293:foil": 1,
        "mmq:294:foil": 1,
        "mmq:295:foil": 1,
        "mmq:296:foil": 1,
        "mmq:298:foil": 1,
        "mmq:299:foil": 1,
        "mmq:302:foil": 1,
        "mmq:303:foil": 1,
        "mmq:304:foil": 1,
        "mmq:305:foil": 1,
        "mmq:306:foil": 1,
        "mmq:307:foil": 1,
        "mmq:309:foil": 1,
        "mmq:311:foil": 1,
        "mmq:312:foil": 1,
        "mmq:313:foil": 1,
        "mmq:315:foil": 1,
        "mmq:316:foil": 1,
        "mmq:320:foil": 1,
        "mmq:324:foil": 1,
        "mmq:330:foil": 1,
        "mmq:3:foil": 1,
        "mmq:40:foil": 1,
        "mmq:41:foil": 1,
        "mmq:44:foil": 1,
        "mmq:47:foil": 1,
        "mmq:49:foil": 1,
        "mmq:56:foil": 1,
        "mmq:58:foil": 1,
        "mmq:62:foil": 1,
        "mmq:66:foil": 1,
        "mmq:70:foil": 1,
        "mmq:77:foil": 1,
        "mmq:79:foil": 1,
        "mmq:86:foil": 1,
        "mmq:87:foil": 1,
        "mmq:89:foil": 1,
        "mmq:8:foil": 1,
        "mmq:92:foil": 1,
        "mmq:96:foil": 1,
        "mmq:97:foil": 1,
        "mmq:99:foil": 1,
        "mmq:9:foil": 1
      }
    }
  },
  "source_set_codes": [
    "mmq"
  ]
}